LICENSE
MANIFEST.in
README.md
README.rst
setup.py
datefeatures/__init__.py
datefeatures/datecomponents.py
datefeatures/monthcircle.py
datefeatures/shoppingholiday.py
datefeatures/timecircle.py
datefeatures.egg-info/PKG-INFO
datefeatures.egg-info/SOURCES.txt
datefeatures.egg-info/dependency_links.txt
datefeatures.egg-info/requires.txt
datefeatures.egg-info/top_level.txt
datefeatures.egg-info/zip-safe
test/__init__.py
test/test_datecomponents.py
test/test_monthcircle.py
test/test_shoppingholidays.py