Metadata-Version: 1.2
Name: datefeatures
Version: 0.3.2
Summary: Feature engineering sklearn transformer for dates
Home-page: http://github.com/kmedian/datefeatures
Author: Ulf Hamster
Author-email: 554c46@gmail.com
License: Apache License 2.0
Platform: UNKNOWN
Requires-Python: >=3.6
